zarx/__init__.py
zarx/config.py
zarx/exceptions.py
zarx/data/__init__.py
zarx/data/augmentation.py
zarx/data/bin_dataset.py
zarx/data/cleaner.py
zarx/data/cli.py
zarx/data/converter.py
zarx/data/inspector.py
zarx/data/loader.py
zarx/data/pipeline.py
zarx/data/processor.py
zarx/data/sampling.py
zarx/data/sharded_dataset.py
zarx/data/validation.py
zarx/data/formats/__init__.py
zarx/data/formats/base.py
zarx/data/formats/json.py
zarx/data/formats/jsonl.py
zarx/data/formats/txt.py
zarx/model/__init__.py
zarx/model/base.py
zarx/model/ssm.py
zarx/model/zmoe.py
zarx/model/components/__init__.py
zarx/model/components/cot_vector.py
zarx/model/components/hass_block.py
zarx/model/components/merger.py
zarx/model/components/routing.py
zarx/models/__init__.py
zarx/models/registry.py
zarx/models/igris/__init__.py
zarx/models/igris/model.py
zarx/models/igris/variants.py
zarx/tokenizer/__init__.py
zarx/tokenizer/adapter.py
zarx/tokenizer/advanced.py
zarx/tokenizer/analysis.py
zarx/tokenizer/base.py
zarx/tokenizer/cache.py
zarx/tokenizer/evaluation.py
zarx/tokenizer/loader.py
zarx/tokenizer/streaming.py
zarx/tokenizer/trainer.py
zarx/tokenizer/utils.py
zarx/training/__init__.py
zarx/training/checkpoint.py
zarx/training/continuation.py
zarx/training/state.py
zarx/training/trainer.py
zarx/utils/__init__.py
zarx/utils/logger.py
zarx/utils/math_utils.py
zarx/utils/sharding.py
zarx/utils/sppq.py
zarx-0.2.4.dist-info/METADATA
zarx-0.2.4.dist-info/WHEEL
zarx-0.2.4.dist-info/top_level.txt
zarx-0.2.4.dist-info/RECORD
