Metadata-Version: 2.4
Name: zarx
Version: 0.2.4
Summary: Zero-to-AGI Deep Learning Framework
Home-page: https://github.com/Akik-Forazi/zarx.git
Author: Akik Faraji
Author-email: akikfaraji@gmail.com
Classifier: Programming Language :: Python :: 3
Classifier: License :: OSI Approved :: MIT License
Classifier: Operating System :: OS Independent
Classifier: Development Status :: 3 - Alpha
Classifier: Intended Audience :: Developers
Classifier: Intended Audience :: Science/Research
Classifier: Topic :: Scientific/Engineering :: Artificial Intelligence
Classifier: Topic :: Software Development :: Libraries :: Python Modules
Requires-Python: >=3.8
Requires-Dist: torch>=1.10.0
Requires-Dist: numpy>=1.20.0
Requires-Dist: tokenizers>=0.11.0
Requires-Dist: tqdm>=4.0.0
Requires-Dist: pyarrow>=6.0.0
Requires-Dist: pandas>=1.0.0
Requires-Dist: psutil>=5.0.0
Requires-Dist: pyyaml>=5.0.0
Requires-Dist: scipy>=1.0.0
Dynamic: author
Dynamic: author-email
Dynamic: classifier
Dynamic: description
Dynamic: description-content-type
Dynamic: home-page
Dynamic: requires-dist
Dynamic: requires-python
Dynamic: summary
